spb_onprem/__init__.py
spb_onprem/_version.py
spb_onprem/base_model.py
spb_onprem/base_service.py
spb_onprem/base_types.py
spb_onprem/entities.py
spb_onprem/exceptions.py
spb_onprem/searches.py
spb_onprem/activities/__init__.py
spb_onprem/activities/queries.py
spb_onprem/activities/service.py
spb_onprem/activities/entities/__init__.py
spb_onprem/activities/entities/activity.py
spb_onprem/activities/entities/activity_history.py
spb_onprem/activities/params/__init__.py
spb_onprem/activities/params/activities.py
spb_onprem/activities/params/activity.py
spb_onprem/activities/params/create_activity.py
spb_onprem/activities/params/delete_activity.py
spb_onprem/activities/params/get_activity_history.py
spb_onprem/activities/params/start_activity.py
spb_onprem/activities/params/update_activity.py
spb_onprem/activities/params/update_activity_history.py
spb_onprem/charts/__init__.py
spb_onprem/charts/factory.py
spb_onprem/contents/__init__.py
spb_onprem/contents/queries.py
spb_onprem/contents/service.py
spb_onprem/contents/entities/__init__.py
spb_onprem/contents/entities/base_content.py
spb_onprem/contents/entities/content.py
spb_onprem/contents/params/__init__.py
spb_onprem/contents/params/create.py
spb_onprem/contents/params/delete_content.py
spb_onprem/contents/params/get_download_url.py
spb_onprem/contents/params/get_file_download_url.py
spb_onprem/contents/params/get_upload_url.py
spb_onprem/data/__init__.py
spb_onprem/data/queries.py
spb_onprem/data/service.py
spb_onprem/data/entities/__init__.py
spb_onprem/data/entities/annotation.py
spb_onprem/data/entities/comment.py
spb_onprem/data/entities/data.py
spb_onprem/data/entities/data_annotation_stats.py
spb_onprem/data/entities/data_meta.py
spb_onprem/data/entities/data_slice.py
spb_onprem/data/entities/frame.py
spb_onprem/data/entities/prediction.py
spb_onprem/data/entities/scene.py
spb_onprem/data/enums/__init__.py
spb_onprem/data/enums/data_meta_type.py
spb_onprem/data/enums/data_status.py
superb_ai_onprem-1.6.3.dist-info/licenses/LICENSE
superb_ai_onprem-1.6.3.dist-info/METADATA
superb_ai_onprem-1.6.3.dist-info/WHEEL
superb_ai_onprem-1.6.3.dist-info/top_level.txt
superb_ai_onprem-1.6.3.dist-info/RECORD
