Metadata-Version: 2.4
Name: superb-ai-onprem
Version: 1.6.3
Summary: Python SDK for Superb AI On-premise
Home-page: https://github.com/Superb-AI-Suite/superb-ai-onprem-python
Author: Superb AI
Author-email: support@superb-ai.com
Classifier: Programming Language :: Python :: 3
Classifier: License :: OSI Approved :: MIT License
Classifier: Operating System :: OS Independent
Requires-Python: >=3.8
License-File: LICENSE
Requires-Dist: requests>=2.22.0
Requires-Dist: urllib3>=1.21.1
Requires-Dist: pydantic>=1.8.0
Dynamic: author
Dynamic: author-email
Dynamic: classifier
Dynamic: description
Dynamic: description-content-type
Dynamic: home-page
Dynamic: license-file
Dynamic: requires-dist
Dynamic: requires-python
Dynamic: summary
